django_darenme_polls-0.1.dist-info/DESCRIPTION.rst
django_darenme_polls-0.1.dist-info/METADATA
django_darenme_polls-0.1.dist-info/RECORD
django_darenme_polls-0.1.dist-info/WHEEL
django_darenme_polls-0.1.dist-info/metadata.json
django_darenme_polls-0.1.dist-info/top_level.txt
polls/__init__.py
polls/admin.py
polls/apps.py
polls/models.py
polls/tests.py
polls/urls.py
polls/views.py
polls/migrations/0001_initial.py
polls/migrations/0002_auto_20170118_2045.py
polls/migrations/__init__.py
polls/static/polls/style.css
polls/static/polls/images/background.jpg
polls/templates/polls/detail.html
polls/templates/polls/index.html
polls/templates/polls/result.html
